Workbook

Sheet 前提条件
A1: off r39'x ランニングコスト試算 ― 前提条件
A2: 青字＝編集可能な入力値／黄色塗り＝特に重要な仮定値（要調整）。黒字の計算式は変更しないでください。
A4: 項目 | B4: 値 | C4: 単位 | D4: 備考・出典
A5: 為替レート
A6: USD → JPY 為替レート | B6: 156 | C6: 円/USD | D6: XE.com 参考レート（2026年9月時点の目安。実際の請求時レートにより変動）
A7: 規模条件（ユーザー提示）
A8: 登録利用ユーザー数 | B8: 300 | C8: 名 | D8: ユーザー提示条件
A9: 同時利用ユーザー数 | B9: 50 | C9: 名 | D9: ユーザー提示条件。Railway/Supabaseの必要スペック見積りの前提
A10: 決済シナリオ ― 通常月（閑散期）
A11: 決済件数（通常月） | B11: 20 | C11: 件/月 | D11: 仮定値・要調整
A12: 平均決済単価（通常月） | B12: 4000 | C12: 円 | D12: 仮定値・要調整
A13: 返金件数（通常月） | B13: 1 | C13: 件/月 | D13: 仮定値・要調整（全額返金のみ、運営判断で実行という運用を想定）
A14: 決済シナリオ ― 繁忙月（販売開始・イベント当日を含む月）
A15: 決済件数（繁忙月） | B15: 250 | C15: 件/月 | D15: 仮定値・要調整（決済失敗の再試行分を含む延べ件数）
A16: 平均決済単価（繁忙月） | B16: 5000 | C16: 円 | D16: 仮定値・要調整
A17: 返金件数（繁忙月） | B17: 5 | C17: 件/月 | D17: 仮定値・要調整
A18: メール配信（決済/返金通知＋ニュース配信）
A19: 月間送信メール数（通常月） | B19: 500 | C19: 通/月 | D19: 仮定値・要調整
A20: 月間送信メール数（繁忙月） | B20: 3000 | C20: 通/月 | D20: 仮定値・要調整（ニュース一斉配信を含む）
A21: Webデータ転送量（公開サイト・ニュース・催し物掲載を含む）
A22: 月間データ転送量（通常月） | B22: 50 | C22: GB/月 | D22: 仮定値・要調整
A23: 月間データ転送量（繁忙月） | B23: 300 | C23: GB/月 | D23: 仮定値・要調整（アクセス集中・画像掲載増を想定）
A24: Stripe手数料率（2026年9月時点、公式サイト参照）
A25: カード決済手数料率 | B25: 0.036 | C25: % | D25: Stripe公式 stripe.com/jp/pricing
A26: コンビニ払い手数料率 | B26: 0.036 | C26: % | D26: Stripe公式 stripe.com/jp/pricing（最低手数料は別行）
A27: コンビニ払い 最低手数料 | B27: 120 | C27: 円/件 | D27: Stripe公式 stripe.com/jp/pricing
A28: コンビニ払い 返金時の追加手数料 | B28: 275 | C28: 円/件 | D28: Stripe公式（¥250＋消費税10%）。カード返金の追加手数料は公式サイトに明記なし（要Stripeサポート確認）

Sheet 固定費
A1: 固定費（月額サブスクリプション費用）
A3: サービス | B3: プラン | C3: 月額 (USD) | D3: 月額 (円) | E3: 用途・備考（出典）
A4: Vercel | B4: Pro | C4: 20 | D4: =C4*前提条件!$B$6 -> 3120 | E4: Webサイト（公開情報・ニュース配信・催し物掲載・購入導線）のホスティング。商用のイベント運営サイトのためHobby（個人利用規約）ではなくProを想定。Fast Data Transfer 1TB/月・Edge Requests 10M/月・Function Invocations 1M/月を含む。出典: vercel.com/pricing
A5: Railway | B5: Pro（月額最低利用額） | C5: 20 | D5: =C5*前提条件!$B$6 -> 3120 | E5: APIサーバー（Hono）ホスティング。Proプランは$20/月がクレジットとしての最低利用額（=実質の固定費フロア）。実際のCPU/メモリ従量課金がこれを超えた分は「変動費」シートで計上。出典: railway.com/pricing
A6: Supabase | B6: Pro | C6: 25 | D6: =C6*前提条件!$B$6 -> 3900 | E6: PostgreSQL データベース + Auth（認証）。DB 8GB・MAU 100,000名までを含み、登録300名規模であれば通常は追加費用なしで収まる。$10/月分のコンピュートクレジットを含む。出典: supabase.com/pricing
A7: Resend | B7: Pro | C7: 20 | D7: =C7*前提条件!$B$6 -> 3120 | E7: 決済/返金通知メール、ニュース一斉配信用のメール送信基盤。50,000通/月まで含み、日次上限なし。Freeプラン（3,000通/月・100通/日の日次上限あり）はニュース一斉配信時に日次上限へ抵触するリスクがあるためPro想定。出典: resend.com/pricing
A8: 固定費 合計（月額） | C8: =SUM(C4:C7) -> 85 | D8: =SUM(D4:D7) -> 13260

Sheet 変動費
A1: 変動費（利用量に応じて発生する費用）
A2: 「通常月」「繁忙月」は前提条件シートの決済・メール・データ転送の仮定値に連動して自動計算されます。
A3: 項目 | B3: 単価・算出方法 | C3: 通常月 数量 | D3: 通常月 コスト(円) | E3: 繁忙月 数量 | F3: 繁忙月 コスト(円) | G3: 備考・出典
A4: Stripe 決済手数料（カード＋コンビニ払い） | B4: 決済総額(GMV) × 3.6% | C4: =前提条件!$B$11*前提条件!$B$12 -> 80000 | D4: =C4*前提条件!$B$25 -> 2880 | E4: =前提条件!$B$15*前提条件!$B$16 -> 1250000 | F4: =E4*前提条件!$B$25 -> 45000 | G4: カード・コンビニ払いとも一律3.6%として概算（コンビニ払いの最低手数料¥120は通常想定する平均単価では下回らない）。決済総額(GMV)＝決済件数×平均決済単価。出典: stripe.com/jp/pricing
A5: Stripe コンビニ払い返金の追加手数料 | B5: 返金件数 × ¥275/件 | C5: =前提条件!$B$13 -> 1 | D5: =C5*前提条件!$B$28 -> 275 | E5: =前提条件!$B$17 -> 5 | F5: =E5*前提条件!$B$28 -> 1375 | G5: 全額返金のみ・運営判断でのみ実行という運用を想定。カード返金の追加手数料はStripe公式サイトに明記がないため0円と仮定（要Stripeサポートへの確認・別途Open Issue）。
A6: Railway 従量課金（$20クレジット超過分） | B6: CPU $0.00000772/vCPU秒、メモリ $0.00000386/GB秒 | C6: 0 | D6: =C6*前提条件!$B$6 -> 0 | E6: 15 | F6: =E6*前提条件!$B$6 -> 2340 | G6: 同時接続50名規模のAPIサーバー負荷は通常月なら$20クレジット内に収まる想定（0ドル）。繁忙月はアクセス集中・Webhook処理増を見込み$15程度の超過を保守的に仮置き（要実測での見直し）。出典: railway.com/pricing
A7: Supabase 従量課金（Storage/Egress超過分） | B7: Egress $0.09/GB、Storage $0.0213/GB（250GB/100GB超過分） | C7: 0 | D7: =C7*前提条件!$B$6 -> 0 | E7: 5 | F7: =E7*前提条件!$B$6 -> 780 | G7: DB 8GB・MAU 100,000名はPro込み枠内で登録300名規模なら通常発生しない。催し物掲載等の画像配信量が多い繁忙月はStorage Egress超過を$5程度保守的に仮置き（要実測での見直し）。出典: supabase.com/pricing
A8: Vercel 従量課金（帯域・リクエスト超過分） | B8: Fast Data Transfer $0.15/GB（1TB/月超過分） | C8: =前提条件!$B$22 -> 50 | D8: 0 | E8: =前提条件!$B$23 -> 300 | F8: 0 | G8: Proプランの含まれるFast Data Transfer 1TB(=1,024GB)/月に対し、通常月50GB・繁忙月300GBはいずれも枠内のため追加費用なし。枠を超える場合は$0.15/GBが加算される。出典: vercel.com/pricing
A9: Resend 従量課金（送信通数超過分） | B9: $0.90 / 1,000通（50,000通/月超過分） | C9: =前提条件!$B$19 -> 500 | D9: 0 | E9: =前提条件!$B$20 -> 3000 | F9: 0 | G9: Proプラン included枠50,000通/月に対し、通常月500通・繁忙月3,000通はいずれも枠内のため追加費用なし。出典: resend.com/pricing
A10: 変動費 合計（月額） | D10: =SUM(D4:D9) -> 3155 | F10: =SUM(F4:F9) -> 49495

Sheet サマリー
A1: off r39'x ランニングコスト試算 ― サマリー
A3: 項目 | B3: 通常月 | C3: 繁忙月 | D3: 備考
A4: 固定費 合計（月額） | B4: =固定費!$D$8 -> 13260 | C4: =固定費!$D$8 -> 13260 | D4: Vercel・Railway・Supabase・Resendの月額サブスクリプション合計（利用量に依存しない）
A5: 変動費 合計（月額） | B5: =変動費!$D$10 -> 3155 | C5: =変動費!$F$10 -> 49495 | D5: Stripe決済/返金手数料＋各サービスの従量課金超過分（前提条件シートの仮定値で自動計算）
A6: 月額合計 | B6: =B4+B5 -> 16415 | C6: =C4+C5 -> 62755 | D6: 固定費＋変動費
A8: 年間試算
A9: 繁忙月の想定回数（年間、販売開始月・イベント開催月等） | B9: 2 | C9: 仮定値・要調整（チケット販売開始月、イベント開催月を想定）
A10: 年間ランニングコスト試算 | B10: =B6*(12-B9)+C6*B9 -> 289660 | C10: ＝月額合計(通常月)×通常月数＋月額合計(繁忙月)×繁忙月数（消費税別）
A12: 注記・前提条件のまとめ
A13: ・対象スタック: Vercel（Webホスティング）／Railway（APIホスティング）／Supabase（PostgreSQL DB + Auth）／Stripe（決済・返金）／Resend（メール配信）。off r39'x の仕様書（000-project-constitution.md ほか）が定める標準技術構成（PRJ-060）に基づく。
A14: ・「決済、返金、ログ確認などの利用」は、上記スタックの管理画面・監査ログ機能の範囲内で完結する想定とし、別途のBI/監視SaaS費用は計上していない。
A15: ・「Webページを静的ホスティング」は、Vercel上でのNext.js（App Router）による静的生成/ISR中心の配信（ニュース配信・催し物掲載を含む公開サイト）として整理し、Vercelの固定費・変動費側に計上した。
A16: ・登録300名・同時50名規模は、各サービスのPro/Hobbyプランの下限枠に対して小規模であり、基本的にはPro plan（商用利用・SLA・チーム機能のため）の固定費内で収まる設計とした。
A17: ・決済件数・平均単価・メール数・データ転送量は仮の仮定値。前提条件シートの黄色セルを実績・事業計画に合わせて更新すると、本シートの金額は自動的に再計算される。
A18: ・為替（USD→JPY）は変動するため、実際の請求額は請求時点のレートにより前後する。
A19: ・本試算はインフラ利用料および決済手数料のみを対象とし、消費税、ドメイン費用、開発・運用人件費、第三者監査費用等は含まない。
